hyccup/__init__.py
hyccup/compiler.hy
hyccup/core.hy
hyccup/definition.hy
hyccup/element.hy
hyccup/form.hy
hyccup/page.hy
hyccup/util.hy
hyccup-1.1.0.dist-info/LICENSE.txt
hyccup-1.1.0.dist-info/METADATA
hyccup-1.1.0.dist-info/WHEEL
hyccup-1.1.0.dist-info/RECORD
