Metadata-Version: 2.1
Name: hyccup
Version: 1.1.0
Summary: A port of Clojure Hiccup for Hy
Home-page: https://github.com/Arkelis/hyccup
License: MIT
Keywords: template,html,hiccup,hy
Author: Guillaume Fayard
Author-email: guillaume.fayard@pycolore.fr
Requires-Python: >=3.9,<3.11
Classifier: License :: OSI Approved :: MIT License
Classifier: Programming Language :: Python :: 3
Classifier: Programming Language :: Python :: 3.9
Classifier: Programming Language :: Python :: 3.10
Requires-Dist: astor (>=0,<1)
Requires-Dist: hy (==0.26.0)
Requires-Dist: hyrule
Requires-Dist: toolz
Project-URL: Documentation, https://hyccup.pycolore.fr
Project-URL: Repository, https://github.com/Arkelis/hyccup
